ahab/__init__.py
ahab/cli.py
ahab/job.py
ahab/job_command.py
ahab_lib-1.0.1.dist-info/entry_points.txt
ahab_lib-1.0.1.dist-info/LICENSE
ahab_lib-1.0.1.dist-info/METADATA
ahab_lib-1.0.1.dist-info/WHEEL
ahab_lib-1.0.1.dist-info/RECORD
