Metadata-Version: 2.1
Name: ahab-lib
Version: 1.0.1
Summary: Python CLI library for interacting with ahab cloud API and Kubernetes systems.
Home-page: https://tuple.xyz/solutions/ahab
License: Copyright 2024, Tuple, LLC. All rights reserved.
Keywords: ahab,bioinformatics,genomics,computational biology,data science,machine learning,ai,Kubernetes,cloud,pipelines
Author: Colby T. Ford
Author-email: colby@tuple.xyz
Requires-Python: >=3.7,<4.0
Classifier: License :: Other/Proprietary License
Classifier: Programming Language :: Python
Classifier: Programming Language :: Python :: 3
Classifier: Programming Language :: Python :: 3.7
Classifier: Programming Language :: Python :: 3.8
Classifier: Programming Language :: Python :: 3.9
Classifier: Programming Language :: Python :: 3.10
Classifier: Programming Language :: Python :: 3.11
Classifier: Programming Language :: Python :: 3.12
Classifier: Topic :: Scientific/Engineering :: Bio-Informatics
Requires-Dist: cleo (>=2.1.0,<3.0.0)
Requires-Dist: requests (>=2.28,<3.0)
Project-URL: Repository, https://github.com/tuplexyz/ahab-lib
